add2num/__init__.py
add2num-0.1.3.dist-info/WHEEL
add2num-0.1.3.dist-info/entry_points.txt
add2num-0.1.3.dist-info/METADATA
add2num-0.1.3.dist-info/RECORD
