Metadata-Version: 2.3
Name: add2num
Version: 0.1.3
Summary: Add your description here
Author: 王涛
Author-email: 王涛 <wtlit@qq.com>
Requires-Dist: mcp[cli]>=1.26.0
Requires-Python: >=3.11
